{
  "start_time": "2023-09-21 00:04:04",
  "rcvTow": 317059.992,
  "week": 2280,
  "leapS": 18,
  "numMeas": 52,
  "leapSec": 1,
  "clkReset": 0,
  "reserved1": 1358081,
  "prMes_01": 23496284.692640185,
  "cpMes_01": 123473935.55179548,
  "doMes_01": -1270.392333984375,
  "gnssId_01": 2,
  "svId_01": 31,
  "sigId_01": 0,
  "freqId_01": 0,
  "locktime_01": 64500,
  "cno_01": 42,
  "prStd_01": 4,
  "cpStd_01": 1,
  "doStd_01": 6,
  "prValid_01": 1,
  "cpValid_01": 1,
  "halfCyc_01": 1,
  "subHalfCyc_01": 0,
  "reserved3_01": 0,
  "prMes_02": 34838582.49957802,
  "cpMes_02": 183078012.28518504,
  "doMes_02": -702.91064453125,
  "gnssId_02": 5,
  "svId_02": 4,
  "sigId_02": 0,
  "freqId_02": 0,
  "locktime_02": 64500,
  "cno_02": 43,
  "prStd_02": 3,
  "cpStd_02": 2,
  "doStd_02": 6,
  "prValid_02": 1,
  "cpValid_02": 1,
  "halfCyc_02": 1,
  "subHalfCyc_02": 1,
  "reserved3_02": 0,
  "prMes_03": 18567525.450776987,
  "cpMes_03": 97573003.01967216,
  "doMes_03": 1664.1722412109375,
  "gnssId_03": 0,
  "svId_03": 7,
  "sigId_03": 0,
  "freqId_03": 0,
  "locktime_03": 64500,
  "cno_03": 33,
  "prStd_03": 6,
  "cpStd_03": 4,
  "doStd_03": 8,
  "prValid_03": 1,
  "cpValid_03": 1,
  "halfCyc_03": 1,
  "subHalfCyc_03": 0,
  "reserved3_03": 0,
  "prMes_04": 22076237.785613224,
  "cpMes_04": 116011368.79232904,
  "doMes_04": -155.343994140625,
  "gnssId_04": 2,
  "svId_04": 24,
  "sigId_04": 0,
  "freqId_04": 0,
  "locktime_04": 64500,
  "cno_04": 47,
  "prStd_04": 3,
  "cpStd_04": 1,
  "doStd_04": 5,
  "prValid_04": 1,
  "cpValid_04": 1,
  "halfCyc_04": 1,
  "subHalfCyc_04": 0,
  "reserved3_04": 0,
  "prMes_05": 34163388.98176117,
  "cpMes_05": 177897820.20900723,
  "doMes_05": -1098.907470703125,
  "gnssId_05": 3,
  "svId_05": 16,
  "sigId_05": 0,
  "freqId_05": 0,
  "locktime_05": 64500,
  "cno_05": 40,
  "prStd_05": 4,
  "cpStd_05": 2,
  "doStd_05": 7,
  "prValid_05": 1,
  "cpValid_05": 1,
  "halfCyc_05": 1,
  "subHalfCyc_05": 1,
  "reserved3_05": 0,
  "prMes_06": 19502161.27702475,
  "cpMes_06": 101552898.13274471,
  "doMes_06": -1113.233154296875,
  "gnssId_06": 3,
  "svId_06": 29,
  "sigId_06": 0,
  "freqId_06": 0,
  "locktime_06": 64500,
  "cno_06": 42,
  "prStd_06": 3,
  "cpStd_06": 1,
  "doStd_06": 6,
  "prValid_06": 1,
  "cpValid_06": 1,
  "halfCyc_06": 1,
  "subHalfCyc_06": 1,
  "reserved3_06": 0,
  "prMes_07": 34777852.89592718,
  "cpMes_07": 181097465.94604632,
  "doMes_07": -1408.0628662109375,
  "gnssId_07": 3,
  "svId_07": 39,
  "sigId_07": 0,
  "freqId_07": 0,
  "locktime_07": 64500,
  "cno_07": 38,
  "prStd_07": 4,
  "cpStd_07": 2,
  "doStd_07": 7,
  "prValid_07": 1,
  "cpValid_07": 1,
  "halfCyc_07": 1,
  "subHalfCyc_07": 1,
  "reserved3_07": 0,
  "prMes_08": 34283356.90135103,
  "cpMes_08": 178522789.50835925,
  "doMes_08": -903.9153442382812,
  "gnssId_08": 3,
  "svId_08": 40,
  "sigId_08": 0,
  "freqId_08": 0,
  "locktime_08": 64500,
  "cno_08": 47,
  "prStd_08": 3,
  "cpStd_08": 1,
  "doStd_08": 5,
  "prValid_08": 1,
  "cpValid_08": 1,
  "halfCyc_08": 1,
  "subHalfCyc_08": 0,
  "reserved3_08": 0,
  "prMes_09": 34361181.10720161,
  "cpMes_09": 178927686.27332544,
  "doMes_09": -586.814453125,
  "gnssId_09": 3,
  "svId_09": 10,
  "sigId_09": 0,
  "freqId_09": 0,
  "locktime_09": 0,
  "cno_09": 25,
  "prStd_09": 8,
  "cpStd_09": 15,
  "doStd_09": 10,
  "prValid_09": 1,
  "cpValid_09": 0,
  "halfCyc_09": 0,
  "subHalfCyc_09": 0,
  "reserved3_09": 0,
  "prMes_10": 33308766.993052058,
  "cpMes_10": 173447592.3879222,
  "doMes_10": -521.2890625,
  "gnssId_10": 3,
  "svId_10": 9,
  "sigId_10": 0,
  "freqId_10": 0,
  "locktime_10": 64500,
  "cno_10": 37,
  "prStd_10": 5,
  "cpStd_10": 3,
  "doStd_10": 7,
  "prValid_10": 1,
  "cpValid_10": 1,
  "halfCyc_10": 1,
  "subHalfCyc_10": 1,
  "reserved3_10": 0,
  "prMes_11": 18771602.966585234,
  "cpMes_11": 100309755.5178829,
  "doMes_11": -877.9765625,
  "gnssId_11": 6,
  "svId_11": 11,
  "sigId_11": 0,
  "freqId_11": 7,
  "locktime_11": 64500,
  "cno_11": 50,
  "prStd_11": 5,
  "cpStd_11": 1,
  "doStd_11": 5,
  "prValid_11": 1,
  "cpValid_11": 1,
  "halfCyc_11": 1,
  "subHalfCyc_11": 1,
  "reserved3_11": 0,
  "prMes_12": 19180630.161217537,
  "cpMes_12": 102315528.28040534,
  "doMes_12": -3285.00244140625,
  "gnssId_12": 6,
  "svId_12": 255,
  "sigId_12": 0,
  "freqId_12": 2,
  "locktime_12": 16000,
  "cno_12": 44,
  "prStd_12": 5,
  "cpStd_12": 1,
  "doStd_12": 6,
  "prValid_12": 1,
  "cpValid_12": 1,
  "halfCyc_12": 1,
  "subHalfCyc_12": 1,
  "reserved3_12": 0,
  "prMes_13": 20541944.38926066,
  "cpMes_13": 109615750.80858494,
  "doMes_13": -2168.22021484375,
  "gnssId_13": 6,
  "svId_13": 2,
  "sigId_13": 0,
  "freqId_13": 3,
  "locktime_13": 0,
  "cno_13": 11,
  "prStd_13": 10,
  "cpStd_13": 15,
  "doStd_13": 12,
  "prValid_13": 1,
  "cpValid_13": 0,
  "halfCyc_13": 0,
  "subHalfCyc_13": 0,
  "reserved3_13": 0,
  "prMes_14": 18851975.253858376,
  "cpMes_14": 99067794.51655328,
  "doMes_14": -2695.440673828125,
  "gnssId_14": 0,
  "svId_14": 8,
  "sigId_14": 0,
  "freqId_14": 0,
  "locktime_14": 64500,
  "cno_14": 43,
  "prStd_14": 3,
  "cpStd_14": 2,
  "doStd_14": 6,
  "prValid_14": 1,
  "cpValid_14": 1,
  "halfCyc_14": 1,
  "subHalfCyc_14": 1,
  "reserved3_14": 0,
  "prMes_15": 36265300.68194398,
  "cpMes_15": 190575753.74656767,
  "doMes_15": -825.761962890625,
  "gnssId_15": 5,
  "svId_15": 3,
  "sigId_15": 0,
  "freqId_15": 0,
  "locktime_15": 64500,
  "cno_15": 44,
  "prStd_15": 3,
  "cpStd_15": 1,
  "doStd_15": 6,
  "prValid_15": 1,
  "cpValid_15": 1,
  "halfCyc_15": 1,
  "subHalfCyc_15": 1,
  "reserved3_15": 0,
  "prMes_16": 34735433.2617837,
  "cpMes_16": 182535937.72778118,
  "doMes_16": -334.423095703125,
  "gnssId_16": 5,
  "svId_16": 7,
  "sigId_16": 0,
  "freqId_16": 0,
  "locktime_16": 64500,
  "cno_16": 31,
  "prStd_16": 6,
  "cpStd_16": 7,
  "doStd_16": 9,
  "prValid_16": 1,
  "cpValid_16": 1,
  "halfCyc_16": 1,
  "subHalfCyc_16": 0,
  "reserved3_16": 0,
  "prMes_17": 22473054.708078884,
  "cpMes_17": 118096853.42832473,
  "doMes_17": 767.872314453125,
  "gnssId_17": 2,
  "svId_17": 12,
  "sigId_17": 0,
  "freqId_17": 0,
  "locktime_17": 64500,
  "cno_17": 41,
  "prStd_17": 4,
  "cpStd_17": 2,
  "doStd_17": 6,
  "prValid_17": 1,
  "cpValid_17": 1,
  "halfCyc_17": 1,
  "subHalfCyc_17": 0,
  "reserved3_17": 0,
  "prMes_18": 33964693.13181048,
  "cpMes_18": 176863258.89282352,
  "doMes_18": -658.717041015625,
  "gnssId_18": 3,
  "svId_18": 7,
  "sigId_18": 0,
  "freqId_18": 0,
  "locktime_18": 64500,
  "cno_18": 41,
  "prStd_18": 3,
  "cpStd_18": 2,
  "doStd_18": 6,
  "prValid_18": 1,
  "cpValid_18": 1,
  "halfCyc_18": 1,
  "subHalfCyc_18": 1,
  "reserved3_18": 0,
  "prMes_19": 33770832.553968154,
  "cpMes_19": 175853677.1678135,
  "doMes_19": -1005.9060668945312,
  "gnssId_19": 3,
  "svId_19": 6,
  "sigId_19": 0,
  "freqId_19": 0,
  "locktime_19": 64500,
  "cno_19": 39,
  "prStd_19": 4,
  "cpStd_19": 2,
  "doStd_19": 7,
  "prValid_19": 1,
  "cpValid_19": 1,
  "halfCyc_19": 1,
  "subHalfCyc_19": 1,
  "reserved3_19": 0,
  "prMes_20": 17093433.599793907,
  "cpMes_20": 91246092.85810652,
  "doMes_20": 520.8353881835938,
  "gnssId_20": 6,
  "svId_20": 22,
  "sigId_20": 0,
  "freqId_20": 4,
  "locktime_20": 64500,
  "cno_20": 50,
  "prStd_20": 5,
  "cpStd_20": 1,
  "doStd_20": 5,
  "prValid_20": 1,
  "cpValid_20": 1,
  "halfCyc_20": 1,
  "subHalfCyc_20": 1,
  "reserved3_20": 0,
  "prMes_21": 18736602.317549918,
  "cpMes_21": 100087516.75766021,
  "doMes_21": 1526.3271484375,
  "gnssId_21": 6,
  "svId_21": 12,
  "sigId_21": 0,
  "freqId_21": 6,
  "locktime_21": 64500,
  "cno_21": 51,
  "prStd_21": 5,
  "cpStd_21": 1,
  "doStd_21": 4,
  "prValid_21": 1,
  "cpValid_21": 1,
  "halfCyc_21": 1,
  "subHalfCyc_21": 1,
  "reserved3_21": 0,
  "prMes_22": 18855270.516244717,
  "cpMes_22": 100898696.49199326,
  "doMes_22": -3195.20556640625,
  "gnssId_22": 6,
  "svId_22": 21,
  "sigId_22": 0,
  "freqId_22": 11,
  "locktime_22": 64500,
  "cno_22": 48,
  "prStd_22": 5,
  "cpStd_22": 1,
  "doStd_22": 5,
  "prValid_22": 1,
  "cpValid_22": 1,
  "halfCyc_22": 1,
  "subHalfCyc_22": 0,
  "reserved3_22": 0,
  "prMes_23": 23181346.365264263,
  "cpMes_23": 121818878.29964466,
  "doMes_23": -2515.460205078125,
  "gnssId_23": 0,
  "svId_23": 16,
  "sigId_23": 0,
  "freqId_23": 0,
  "locktime_23": 64500,
  "cno_23": 35,
  "prStd_23": 5,
  "cpStd_23": 4,
  "doStd_23": 8,
  "prValid_23": 1,
  "cpValid_23": 1,
  "halfCyc_23": 1,
  "subHalfCyc_23": 1,
  "reserved3_23": 0,
  "prMes_24": 21684189.008312393,
  "cpMes_24": 113951356.04532859,
  "doMes_24": -3828.20947265625,
  "gnssId_24": 0,
  "svId_24": 27,
  "sigId_24": 0,
  "freqId_24": 0,
  "locktime_24": 64500,
  "cno_24": 38,
  "prStd_24": 4,
  "cpStd_24": 2,
  "doStd_24": 7,
  "prValid_24": 1,
  "cpValid_24": 1,
  "halfCyc_24": 1,
  "subHalfCyc_24": 1,
  "reserved3_24": 0,
  "prMes_25": 22687293.937358383,
  "cpMes_25": 119222674.48318507,
  "doMes_25": 1848.8995361328125,
  "gnssId_25": 2,
  "svId_25": 10,
  "sigId_25": 0,
  "freqId_25": 0,
  "locktime_25": 64500,
  "cno_25": 46,
  "prStd_25": 3,
  "cpStd_25": 1,
  "doStd_25": 5,
  "prValid_25": 1,
  "cpValid_25": 1,
  "halfCyc_25": 1,
  "subHalfCyc_25": 0,
  "reserved3_25": 0,
  "prMes_26": 37607594.20008259,
  "cpMes_26": 197629450.79574072,
  "doMes_26": 304.590576171875,
  "gnssId_26": 5,
  "svId_26": 2,
  "sigId_26": 0,
  "freqId_26": 0,
  "locktime_26": 64500,
  "cno_26": 43,
  "prStd_26": 3,
  "cpStd_26": 1,
  "doStd_26": 6,
  "prValid_26": 1,
  "cpValid_26": 1,
  "halfCyc_26": 1,
  "subHalfCyc_26": 0,
  "reserved3_26": 0,
  "prMes_27": 24563277.42081643,
  "cpMes_27": 129080909.31018147,
  "doMes_27": -1761.772705078125,
  "gnssId_27": 2,
  "svId_27": 33,
  "sigId_27": 0,
  "freqId_27": 0,
  "locktime_27": 64500,
  "cno_27": 38,
  "prStd_27": 4,
  "cpStd_27": 2,
  "doStd_27": 7,
  "prValid_27": 1,
  "cpValid_27": 1,
  "halfCyc_27": 1,
  "subHalfCyc_27": 0,
  "reserved3_27": 0,
  "prMes_28": 18635260.192641832,
  "cpMes_28": 97929171.26740408,
  "doMes_28": 90.74437713623047,
  "gnssId_28": 0,
  "svId_28": 21,
  "sigId_28": 0,
  "freqId_28": 0,
  "locktime_28": 64500,
  "cno_28": 48,
  "prStd_28": 3,
  "cpStd_28": 1,
  "doStd_28": 5,
  "prValid_28": 1,
  "cpValid_28": 1,
  "halfCyc_28": 1,
  "subHalfCyc_28": 1,
  "reserved3_28": 0,
  "prMes_29": 19158568.317810927,
  "cpMes_29": 100679074.78937279,
  "doMes_29": 760.238037109375,
  "gnssId_29": 0,
  "svId_29": 2,
  "sigId_29": 0,
  "freqId_29": 0,
  "locktime_29": 64500,
  "cno_29": 47,
  "prStd_29": 3,
  "cpStd_29": 1,
  "doStd_29": 5,
  "prValid_29": 1,
  "cpValid_29": 1,
  "halfCyc_29": 1,
  "subHalfCyc_29": 1,
  "reserved3_29": 0,
  "prMes_30": 34361173.22600426,
  "cpMes_30": 138358213.49431837,
  "doMes_30": -453.8447265625,
  "gnssId_30": 3,
  "svId_30": 10,
  "sigId_30": 2,
  "freqId_30": 0,
  "locktime_30": 8040,
  "cno_30": 27,
  "prStd_30": 7,
  "cpStd_30": 8,
  "doStd_30": 8,
  "prValid_30": 1,
  "cpValid_30": 1,
  "halfCyc_30": 1,
  "subHalfCyc_30": 1,
  "reserved3_30": 0,
  "prMes_31": 33308760.535303865,
  "cpMes_31": 134120677.87368253,
  "doMes_31": -402.740478515625,
  "gnssId_31": 3,
  "svId_31": 9,
  "sigId_31": 2,
  "freqId_31": 0,
  "locktime_31": 64500,
  "cno_31": 38,
  "prStd_31": 4,
  "cpStd_31": 2,
  "doStd_31": 7,
  "prValid_31": 1,
  "cpValid_31": 1,
  "halfCyc_31": 1,
  "subHalfCyc_31": 0,
  "reserved3_31": 0,
  "prMes_32": 22687296.594412964,
  "cpMes_32": 91352513.73016858,
  "doMes_32": 1416.6505126953125,
  "gnssId_32": 2,
  "svId_32": 10,
  "sigId_32": 6,
  "freqId_32": 0,
  "locktime_32": 64500,
  "cno_32": 50,
  "prStd_32": 3,
  "cpStd_32": 1,
  "doStd_32": 4,
  "prValid_32": 1,
  "cpValid_32": 1,
  "halfCyc_32": 1,
  "subHalfCyc_32": 0,
  "reserved3_32": 0,
  "prMes_33": 23496286.757713582,
  "cpMes_33": 94609888.03444043,
  "doMes_33": -973.388916015625,
  "gnssId_33": 2,
  "svId_33": 31,
  "sigId_33": 6,
  "freqId_33": 0,
  "locktime_33": 64500,
  "cno_33": 45,
  "prStd_33": 3,
  "cpStd_33": 1,
  "doStd_33": 6,
  "prValid_33": 1,
  "cpValid_33": 1,
  "halfCyc_33": 1,
  "subHalfCyc_33": 0,
  "reserved3_33": 0,
  "prMes_34": 33964683.352587834,
  "cpMes_34": 136762056.14929795,
  "doMes_34": -509.461669921875,
  "gnssId_34": 3,
  "svId_34": 7,
  "sigId_34": 2,
  "freqId_34": 0,
  "locktime_34": 64500,
  "cno_34": 42,
  "prStd_34": 3,
  "cpStd_34": 2,
  "doStd_34": 6,
  "prValid_34": 1,
  "cpValid_34": 1,
  "halfCyc_34": 1,
  "subHalfCyc_34": 1,
  "reserved3_34": 0,
  "prMes_35": 34163387.263492115,
  "cpMes_35": 137561915.54064265,
  "doMes_35": -849.920654296875,
  "gnssId_35": 3,
  "svId_35": 16,
  "sigId_35": 2,
  "freqId_35": 0,
  "locktime_35": 64500,
  "cno_35": 39,
  "prStd_35": 4,
  "cpStd_35": 2,
  "doStd_35": 7,
  "prValid_35": 1,
  "cpValid_35": 1,
  "halfCyc_35": 1,
  "subHalfCyc_35": 0,
  "reserved3_35": 0,
  "prMes_36": 22076238.26467123,
  "cpMes_36": 88891877.5767266,
  "doMes_36": -119.04540252685547,
  "gnssId_36": 2,
  "svId_36": 24,
  "sigId_36": 6,
  "freqId_36": 0,
  "locktime_36": 64500,
  "cno_36": 50,
  "prStd_36": 3,
  "cpStd_36": 1,
  "doStd_36": 5,
  "prValid_36": 1,
  "cpValid_36": 1,
  "halfCyc_36": 1,
  "subHalfCyc_36": 0,
  "reserved3_36": 0,
  "prMes_37": 33770823.949494176,
  "cpMes_37": 135981225.8748913,
  "doMes_37": -778.04296875,
  "gnssId_37": 3,
  "svId_37": 6,
  "sigId_37": 2,
  "freqId_37": 0,
  "locktime_37": 64500,
  "cno_37": 42,
  "prStd_37": 3,
  "cpStd_37": 2,
  "doStd_37": 6,
  "prValid_37": 1,
  "cpValid_37": 1,
  "halfCyc_37": 1,
  "subHalfCyc_37": 0,
  "reserved3_37": 0,
  "prMes_38": 22473053.82322787,
  "cpMes_38": 90489991.24170169,
  "doMes_38": 587.9931030273438,
  "gnssId_38": 2,
  "svId_38": 12,
  "sigId_38": 6,
  "freqId_38": 0,
  "locktime_38": 64500,
  "cno_38": 45,
  "prStd_38": 3,
  "cpStd_38": 1,
  "doStd_38": 6,
  "prValid_38": 1,
  "cpValid_38": 1,
  "halfCyc_38": 1,
  "subHalfCyc_38": 0,
  "reserved3_38": 0,
  "prMes_39": 24563278.411305416,
  "cpMes_39": 98906600.36317618,
  "doMes_39": -1349.73193359375,
  "gnssId_39": 2,
  "svId_39": 33,
  "sigId_39": 6,
  "freqId_39": 0,
  "locktime_39": 64500,
  "cno_39": 41,
  "prStd_39": 3,
  "cpStd_39": 1,
  "doStd_39": 6,
  "prValid_39": 1,
  "cpValid_39": 1,
  "halfCyc_39": 1,
  "subHalfCyc_39": 0,
  "reserved3_39": 0,
  "prMes_40": 36265298.259314336,
  "cpMes_40": 148500739.2463608,
  "doMes_40": -643.5302734375,
  "gnssId_40": 5,
  "svId_40": 3,
  "sigId_40": 5,
  "freqId_40": 0,
  "locktime_40": 64500,
  "cno_40": 42,
  "prStd_40": 4,
  "cpStd_40": 2,
  "doStd_40": 6,
  "prValid_40": 1,
  "cpValid_40": 1,
  "halfCyc_40": 1,
  "subHalfCyc_40": 0,
  "reserved3_40": 0,
  "prMes_41": 20496475.546305843,
  "cpMes_41": 83929640.59606096,
  "doMes_41": 2090.822509765625,
  "gnssId_41": 0,
  "svId_41": 30,
  "sigId_41": 3,
  "freqId_41": 0,
  "locktime_41": 0,
  "cno_41": 12,
  "prStd_41": 9,
  "cpStd_41": 15,
  "doStd_41": 12,
  "prValid_41": 1,
  "cpValid_41": 0,
  "halfCyc_41": 0,
  "subHalfCyc_41": 0,
  "reserved3_41": 0,
  "prMes_42": 37607592.218385056,
  "cpMes_42": 153996867.802301,
  "doMes_42": 237.16357421875,
  "gnssId_42": 5,
  "svId_42": 2,
  "sigId_42": 5,
  "freqId_42": 0,
  "locktime_42": 64500,
  "cno_42": 41,
  "prStd_42": 4,
  "cpStd_42": 2,
  "doStd_42": 7,
  "prValid_42": 1,
  "cpValid_42": 1,
  "halfCyc_42": 1,
  "subHalfCyc_42": 0,
  "reserved3_42": 0,
  "prMes_43": 18771602.559176534,
  "cpMes_43": 78018711.87198383,
  "doMes_43": -682.8668823242188,
  "gnssId_43": 6,
  "svId_43": 11,
  "sigId_43": 2,
  "freqId_43": 7,
  "locktime_43": 64500,
  "cno_43": 48,
  "prStd_43": 5,
  "cpStd_43": 1,
  "doStd_43": 5,
  "prValid_43": 1,
  "cpValid_43": 1,
  "halfCyc_43": 1,
  "subHalfCyc_43": 1,
  "reserved3_43": 0,
  "prMes_44": 18736602.483093485,
  "cpMes_44": 77845870.83510068,
  "doMes_44": 1187.0419921875,
  "gnssId_44": 6,
  "svId_44": 12,
  "sigId_44": 2,
  "freqId_44": 6,
  "locktime_44": 64500,
  "cno_44": 44,
  "prStd_44": 5,
  "cpStd_44": 1,
  "doStd_44": 6,
  "prValid_44": 1,
  "cpValid_44": 1,
  "halfCyc_44": 1,
  "subHalfCyc_44": 1,
  "reserved3_44": 0,
  "prMes_45": 17093434.262990966,
  "cpMes_45": 70969240.35281487,
  "doMes_45": 405.089111328125,
  "gnssId_45": 6,
  "svId_45": 22,
  "sigId_45": 2,
  "freqId_45": 4,
  "locktime_45": 64500,
  "cno_45": 50,
  "prStd_45": 5,
  "cpStd_45": 1,
  "doStd_45": 4,
  "prValid_45": 1,
  "cpValid_45": 1,
  "halfCyc_45": 1,
  "subHalfCyc_45": 1,
  "reserved3_45": 0,
  "prMes_46": 18855269.287628774,
  "cpMes_46": 78476834.46024536,
  "doMes_46": -2485.22705078125,
  "gnssId_46": 6,
  "svId_46": 21,
  "sigId_46": 2,
  "freqId_46": 11,
  "locktime_46": 64500,
  "cno_46": 44,
  "prStd_46": 5,
  "cpStd_46": 1,
  "doStd_46": 6,
  "prValid_46": 1,
  "cpValid_46": 1,
  "halfCyc_46": 1,
  "subHalfCyc_46": 1,
  "reserved3_46": 0,
  "prMes_47": 34838588.06209821,
  "cpMes_47": 142658249.38828126,
  "doMes_47": -547.7890625,
  "gnssId_47": 5,
  "svId_47": 4,
  "sigId_47": 5,
  "freqId_47": 0,
  "locktime_47": 64500,
  "cno_47": 42,
  "prStd_47": 4,
  "cpStd_47": 2,
  "doStd_47": 6,
  "prValid_47": 1,
  "cpValid_47": 1,
  "halfCyc_47": 1,
  "subHalfCyc_47": 0,
  "reserved3_47": 0,
  "prMes_48": 21684188.489780705,
  "cpMes_48": 88793407.18590665,
  "doMes_48": -2983.34033203125,
  "gnssId_48": 0,
  "svId_48": 27,
  "sigId_48": 3,
  "freqId_48": 0,
  "locktime_48": 64500,
  "cno_48": 42,
  "prStd_48": 4,
  "cpStd_48": 2,
  "doStd_48": 7,
  "prValid_48": 1,
  "cpValid_48": 1,
  "halfCyc_48": 1,
  "subHalfCyc_48": 0,
  "reserved3_48": 0,
  "prMes_49": 18851974.53094974,
  "cpMes_49": 77195748.24574992,
  "doMes_49": -2100.35400390625,
  "gnssId_49": 0,
  "svId_49": 8,
  "sigId_49": 3,
  "freqId_49": 0,
  "locktime_49": 64500,
  "cno_49": 44,
  "prStd_49": 4,
  "cpStd_49": 1,
  "doStd_49": 6,
  "prValid_49": 1,
  "cpValid_49": 1,
  "halfCyc_49": 1,
  "subHalfCyc_49": 0,
  "reserved3_49": 0,
  "prMes_50": 18567517.562459942,
  "cpMes_50": 76030893.26240748,
  "doMes_50": 1296.5576171875,
  "gnssId_50": 0,
  "svId_50": 7,
  "sigId_50": 3,
  "freqId_50": 0,
  "locktime_50": 11480,
  "cno_50": 31,
  "prStd_50": 6,
  "cpStd_50": 7,
  "doStd_50": 9,
  "prValid_50": 1,
  "cpValid_50": 1,
  "halfCyc_50": 1,
  "subHalfCyc_50": 0,
  "reserved3_50": 0,
  "prMes_51": 34735430.37909651,
  "cpMes_51": 142236043.17723513,
  "doMes_51": -260.99609375,
  "gnssId_51": 5,
  "svId_51": 7,
  "sigId_51": 5,
  "freqId_51": 0,
  "locktime_51": 64500,
  "cno_51": 45,
  "prStd_51": 4,
  "cpStd_51": 1,
  "doStd_51": 6,
  "prValid_51": 1,
  "cpValid_51": 1,
  "halfCyc_51": 1,
  "subHalfCyc_51": 0,
  "reserved3_51": 0,
  "prMes_52": 19180633.660380904,
  "cpMes_52": 79578757.32815762,
  "doMes_52": -2555.030517578125,
  "gnssId_52": 6,
  "svId_52": 255,
  "sigId_52": 2,
  "freqId_52": 2,
  "locktime_52": 18000,
  "cno_52": 42,
  "prStd_52": 5,
  "cpStd_52": 2,
  "doStd_52": 6,
  "prValid_52": 1,
  "cpValid_52": 1,
  "halfCyc_52": 1,
  "subHalfCyc_52": 0,
  "reserved3_52": 0
}